PyrootCK/__init__.py
PyrootCK/ioutils.py
PyrootCK/tmvautils.py
PyrootCK/mathutils/__init__.py
PyrootCK/mathutils/asymvar.py
PyrootCK/mathutils/efficiencies.py
PyrootCK/mathutils/misc.py
PyrootCK/mathutils/pandas.py
PyrootCK/patch_uncertainties/__init__.py
PyrootCK/patchers/RooAbsArg.py
PyrootCK/patchers/RooDataHist.py
PyrootCK/patchers/RooFitResult.py
PyrootCK/patchers/RooRealVar.py
PyrootCK/patchers/RooWorkspace.py
PyrootCK/patchers/TAxis.py
PyrootCK/patchers/TFile.py
PyrootCK/patchers/TGraphAsymmErrors.py
PyrootCK/patchers/TGraphErrors.py
PyrootCK/patchers/TH1.py
PyrootCK/patchers/TH2.py
PyrootCK/patchers/TList.py
PyrootCK/patchers/TMatrix.py
PyrootCK/patchers/TMinuit.py
PyrootCK/patchers/TMultiGraph.py
PyrootCK/patchers/TNamed.py
PyrootCK/patchers/TTree.py
PyrootCK/patchers/__init_RooFit__.py
PyrootCK/patchers/__init__.py
PyrootCK-1.0.1.dist-info/LICENSE.txt
PyrootCK-1.0.1.dist-info/METADATA
PyrootCK-1.0.1.dist-info/RECORD
PyrootCK-1.0.1.dist-info/WHEEL
PyrootCK-1.0.1.dist-info/pbr.json
PyrootCK-1.0.1.dist-info/top_level.txt
