Metadata-Version: 2.1
Name: PyrootCK
Version: 1.0.1
Summary: Improving PyROOT for better productivity.
Home-page: https://gitlab.com/ckhurewa/PyrootCK
Author: Chitsanu Khurewathanakul
Author-email: chitsanu.khurewathanakul@gmail.com
License: GNU GPLv3
Platform: unix
Classifier: Development Status :: 4 - Beta
Classifier: Environment :: Console
Classifier: Intended Audience :: Developers
Classifier: Intended Audience :: Information Technology
Classifier: Operating System :: OS Independent
Classifier: Programming Language :: Python :: 2.7
Classifier: Topic :: Utilities
Requires-Python: ~=2.7
Requires-Dist: pyroot-zen
Requires-Dist: uncertainties
Requires-Dist: pandas
Requires-Dist: root-numpy
Requires-Dist: PythonCK
